spotify_web_downloader/__init__.py
spotify_web_downloader/__main__.py
spotify_web_downloader/cli.py
spotify_web_downloader/constants.py
spotify_web_downloader/downloader.py
spotify_web_downloader/downloader_music_video.py
spotify_web_downloader/downloader_song.py
spotify_web_downloader/enums.py
spotify_web_downloader/models.py
spotify_web_downloader/spotify_api.py
spotify_web_downloader/utils.py
spotify_web_downloader-1.8.1.dist-info/entry_points.txt
spotify_web_downloader-1.8.1.dist-info/WHEEL
spotify_web_downloader-1.8.1.dist-info/METADATA
spotify_web_downloader-1.8.1.dist-info/RECORD
