Metadata-Version: 2.1
Name: spotify-web-downloader
Version: 1.8.1
Summary: A Python CLI app for downloading songs and music videos directly from Spotify.
Author: glomatico
Requires-Python: >=3.8
Requires-Dist: click
Requires-Dist: pybase62
Requires-Dist: pywidevine
Requires-Dist: pyyaml
Requires-Dist: yt-dlp
Project-URL: repository, https://github.com/glomatico/spotify-web-downloader
